enstelco/__init__.py
enstelco/cli.py
enstelco/deformations.py
enstelco/main.py
enstelco/solve.py
enstelco/strains.py
enstelco/test.py
enstelco/utils.py
enstelco/elate/elastic.py
enstelco-0.3.dist-info/LICENSE
enstelco-0.3.dist-info/METADATA
enstelco-0.3.dist-info/WHEEL
enstelco-0.3.dist-info/entry_points.txt
enstelco-0.3.dist-info/top_level.txt
enstelco-0.3.dist-info/RECORD
