Metadata-Version: 2.1
Name: enstelco
Version: 0.3
Summary: ENergy-STrain ELastic COnstant calculations made simple!
Home-page: https://github.com/tysours/ENSTELCO
Maintainer: Ty Sours
Maintainer-email: tsours@ucdavis.edu
License: MIT
Project-URL: Source, https://github.com/tysours/ENSTELCO
Project-URL: Tracker, https://github.com/tysours/ENSTELCO/issues
Platform: UNKNOWN
Classifier: Development Status :: 3 - Alpha
Classifier: License :: OSI Approved :: MIT License
Classifier: Operating System :: OS Independent
Classifier: Programming Language :: Python :: 3
Classifier: Intended Audience :: Science/Research
Classifier: Topic :: Scientific/Engineering :: Chemistry
Requires-Python: >=3.6
Requires-Dist: ase
Requires-Dist: nlopt (==2.7.0)
Requires-Dist: spglib
Requires-Dist: rich
